neataco/__init__.py
neataco/aco.py
neataco/distance.py
neataco-1.0.0.dist-info/LICENSE
neataco-1.0.0.dist-info/METADATA
neataco-1.0.0.dist-info/WHEEL
neataco-1.0.0.dist-info/top_level.txt
neataco-1.0.0.dist-info/RECORD
