Metadata-Version: 2.1
Name: neataco
Version: 1.0.0
Summary: Neat ACO is an Ant Colony Optimization algorithm written in pure Python.
Home-page: https://gitlab.com/landreville/neataco
Author: Landreville
License: UNKNOWN
Platform: UNKNOWN
Classifier: Programming Language :: Python
Classifier: Programming Language :: Python :: 3
Classifier: Programming Language :: Python :: Implementation :: PyPy
Classifier: License :: OSI Approved :: GNU Affero General Public License v3
